pyemaps/COPYING
pyemaps/README.md
pyemaps/__config__.py
pyemaps/__init__.py
pyemaps/__main__.py
pyemaps/__version__.py
pyemaps/crystals.py
pyemaps/ddiffs.py
pyemaps/display.py
pyemaps/emcontrols.py
pyemaps/errors.py
pyemaps/fileutils.py
pyemaps/kdiffs.py
pyemaps/license.txt
pyemaps/stackimg.py
pyemaps/xtal.py
pyemaps/CifFile/CifFile_module.py
pyemaps/CifFile/StarFile.py
pyemaps/CifFile/StarScan.cp37-win_amd64.pyd
pyemaps/CifFile/TypeContentsParser.py
pyemaps/CifFile/YappsStarParser_1_0.py
pyemaps/CifFile/YappsStarParser_1_1.py
pyemaps/CifFile/YappsStarParser_2_0.py
pyemaps/CifFile/YappsStarParser_STAR2.py
pyemaps/CifFile/__init__.py
pyemaps/CifFile/parsetab.py
pyemaps/CifFile/yapps3_compiled_rt.py
pyemaps/CifFile/drel/__init__.py
pyemaps/CifFile/drel/drel_ast_yacc.py
pyemaps/CifFile/drel/drel_lex.py
pyemaps/CifFile/drel/drel_runtime.py
pyemaps/CifFile/drel/parsetab.py
pyemaps/CifFile/drel/py_from_ast.py
pyemaps/cdata/Aluminium.xtl
pyemaps/cdata/AluminiumOxide.xtl
pyemaps/cdata/Aluminium_FCC.xtl
pyemaps/cdata/BariumTitanate_180k.xtl
pyemaps/cdata/BariumTitanate_270k.xtl
pyemaps/cdata/BariumTitanate_Tetra.xtl
pyemaps/cdata/BiMnO3.xtl
pyemaps/cdata/Boron_Tetra.xtl
pyemaps/cdata/CadmiumSelenide_Hex.xtl
pyemaps/cdata/CadmiumSulfide_Cubic.xtl
pyemaps/cdata/CadmiumSulfide_Hex.xtl
pyemaps/cdata/Chromium_BCC.xtl
pyemaps/cdata/CoSb3_Skutterudite.xtl
pyemaps/cdata/CopperOxide.xtl
pyemaps/cdata/Copper_FCC.xtl
pyemaps/cdata/Cu2O_Cuprite.xtl
pyemaps/cdata/Diamond.xtl
pyemaps/cdata/ErbiumPyrogermanate.xtl
pyemaps/cdata/FePd_Tetra.xtl
pyemaps/cdata/FeS2_Pyrite.xtl
pyemaps/cdata/GalliumAntimonide.xtl
pyemaps/cdata/GalliumArsenide.xtl
pyemaps/cdata/GalliumNitride.xtl
pyemaps/cdata/Germanium.xtl
pyemaps/cdata/Gold_FCC.xtl
pyemaps/cdata/IndiumArsenide.xtl
pyemaps/cdata/LaMnO3.xtl
pyemaps/cdata/LeadZirconateTitanate.xtl
pyemaps/cdata/Li2MnO3.xtl
pyemaps/cdata/NaFeO2.xtl
pyemaps/cdata/Nb3Sn.xtl
pyemaps/cdata/Pentacene.xtl
pyemaps/cdata/Silicon.xtl
pyemaps/cdata/StrontiumTitanate.xtl
pyemaps-1.1.4.dist-info/COPYING
pyemaps-1.1.4.dist-info/METADATA
pyemaps-1.1.4.dist-info/WHEEL
pyemaps-1.1.4.dist-info/entry_points.txt
pyemaps-1.1.4.dist-info/license.txt
pyemaps-1.1.4.dist-info/top_level.txt
pyemaps-1.1.4.dist-info/RECORD
