Metadata-Version: 2.1
Name: pyemaps
Version: 1.1.4
Summary: A Python Package for Transmission Electron Diffraction Simulations and Crystallographic Computing
Home-page: https://www.emlabsolutions.com
Author: EMLab Solutions, Inc.
Author-email: support@emlabsoftware.com
License: Free for base features. License activation required for extended 4dstem features
Keywords: Transmission,Electron,Diffraction,Simulation,Crystallography,Python
Classifier: Development Status :: 5 - Production/Stable
Classifier: Programming Language :: Python :: 3.7
Classifier: Operating System :: Microsoft :: Windows
Classifier: Topic :: Software Development :: Libraries :: Python Modules
Classifier: Intended Audience :: Science/Research
Requires-Python: >=3.7
License-File: license.txt
License-File: COPYING
Requires-Dist: emaps (>=1.0.8)
Requires-Dist: numpy (>=1.21.2)
Requires-Dist: matplotlib (>=3.2.1)
